[{"id":1,"first_name":"Heinrick Spurrier","email":"hspurrier0@examiner.com","gender":"Male","address":"Zherdevka"},
{"id":2,"first_name":"Niki Kirlin","email":"nkirlin1@census.gov","gender":"Bigender","address":"Baitouli"},
{"id":3,"first_name":"Susette Vitall","email":"svitall2@privacy.gov.au","gender":"Female","address":"Hrastnik"},
{"id":4,"first_name":"Clari Grolmann","email":"cgrolmann3@cpanel.net","gender":"Female","address":"Fenghui"},
{"id":5,"first_name":"Collie Martini","email":"cmartini4@4shared.com","gender":"Female","address":"Camingawan"},
{"id":6,"first_name":"Hieronymus Doogan","email":"hdoogan5@webnode.com","gender":"Male","address":"Cikaduen"},
{"id":7,"first_name":"Randie Cockcroft","email":"rcockcroft6@quantcast.com","gender":"Female","address":"Fès"},
{"id":8,"first_name":"Thorn Sail","email":"tsail7@zdnet.com","gender":"Male","address":"Canghou"},
{"id":9,"first_name":"Casie Luisetti","email":"cluisetti8@ed.gov","gender":"Non-binary","address":"Calle Blancos"},
{"id":10,"first_name":"Merilee Melonby","email":"mmelonby9@fotki.com","gender":"Female","address":"Indramayu"},
{"id":11,"first_name":"Ferne Manwell","email":"fmanwella@theglobeandmail.com","gender":"Bigender","address":"Longhua"},
{"id":12,"first_name":"Judi Sorsbie","email":"jsorsbieb@netscape.com","gender":"Genderqueer","address":"Karangpeton"},
{"id":13,"first_name":"Moria Spellworth","email":"mspellworthc@sourceforge.net","gender":"Female","address":"Tawala"},
{"id":14,"first_name":"Galven Pigne","email":"gpigned@chicagotribune.com","gender":"Male","address":"Mbouda"},
{"id":15,"first_name":"Ashli Bulward","email":"abulwarde@wikipedia.org","gender":"Female","address":"Xiabeisi"},
{"id":16,"first_name":"Kathye Mackriell","email":"kmackriellf@spiegel.de","gender":"Female","address":"Buniaga"},
{"id":17,"first_name":"Kliment Brosh","email":"kbroshg@washington.edu","gender":"Male","address":"Jindong"},
{"id":18,"first_name":"Stanislaus Becraft","email":"sbecrafth@mediafire.com","gender":"Genderfluid","address":"Santander"},
{"id":19,"first_name":"Mareah Gaylard","email":"mgaylardi@senate.gov","gender":"Female","address":"Al Buţayḩah"},
{"id":20,"first_name":"Jamal Dive","email":"jdivej@globo.com","gender":"Male","address":"Sayang Lauq"},
{"id":21,"first_name":"Wanids Alves","email":"walvesk@scientificamerican.com","gender":"Female","address":"Autun"},
{"id":22,"first_name":"Nathaniel Grcic","email":"ngrcicl@taobao.com","gender":"Male","address":"Enschede"},
{"id":23,"first_name":"Joshuah Fleay","email":"jfleaym@europa.eu","gender":"Male","address":"Ciguha Tengah"},
{"id":24,"first_name":"Shell McEnteggart","email":"smcenteggartn@howstuffworks.com","gender":"Polygender","address":"Haguenau"},
{"id":25,"first_name":"Lianne Buckle","email":"lbuckleo@acquirethisname.com","gender":"Female","address":"Urasqui"},
{"id":26,"first_name":"Larissa Dy","email":"ldyp@zdnet.com","gender":"Female","address":"Xuefu"},
{"id":27,"first_name":"Orrin Clewlowe","email":"oclewloweq@posterous.com","gender":"Male","address":"Brody"},
{"id":28,"first_name":"Nita Batterbee","email":"nbatterbeer@hp.com","gender":"Female","address":"Morrinhos"},
{"id":29,"first_name":"Noby Castello","email":"ncastellos@wired.com","gender":"Male","address":"Huzhen"},
{"id":30,"first_name":"Melli Hannon","email":"mhannont@cam.ac.uk","gender":"Female","address":"‘Arīshah"},
{"id":31,"first_name":"Leroi Miller","email":"lmilleru@arstechnica.com","gender":"Male","address":"Raub"},
{"id":32,"first_name":"Ynez Longina","email":"ylonginav@theatlantic.com","gender":"Female","address":"Sarilhos Grandes"},
{"id":33,"first_name":"Boyd Mallabon","email":"bmallabonw@github.com","gender":"Male","address":"Gugut"},
{"id":34,"first_name":"Dame Toffoloni","email":"dtoffolonix@nytimes.com","gender":"Male","address":"Queluz"},
{"id":35,"first_name":"Junina Deluca","email":"jdelucay@census.gov","gender":"Non-binary","address":"Bintuni"},
{"id":36,"first_name":"Margaretta Nutten","email":"mnuttenz@alibaba.com","gender":"Female","address":"Fort Worth"},
{"id":37,"first_name":"Lorant Bonick","email":"lbonick10@1und1.de","gender":"Male","address":"Sudikampir"},
{"id":38,"first_name":"Avram Cristofari","email":"acristofari11@geocities.jp","gender":"Male","address":"Mrzeżyno"},
{"id":39,"first_name":"Millicent Dillintone","email":"mdillintone12@marketwatch.com","gender":"Female","address":"Quilmes"},
{"id":40,"first_name":"Clari Broggio","email":"cbroggio13@buzzfeed.com","gender":"Female","address":"Sudikampir"},
{"id":41,"first_name":"Hortense Gelletly","email":"hgelletly14@ycombinator.com","gender":"Female","address":"Koímisi"},
{"id":42,"first_name":"Lydon Bridywater","email":"lbridywater15@cisco.com","gender":"Male","address":"Bodø"},
{"id":43,"first_name":"Euell Faragher","email":"efaragher16@mysql.com","gender":"Male","address":"Buyunshan"},
{"id":44,"first_name":"Courtenay Kingston","email":"ckingston17@google.co.uk","gender":"Female","address":"Amfíkleia"},
{"id":45,"first_name":"Sophi Garfoot","email":"sgarfoot18@youku.com","gender":"Female","address":"Laylay"},
{"id":46,"first_name":"Dorothea Marquet","email":"dmarquet19@ovh.net","gender":"Female","address":"Winong"},
{"id":47,"first_name":"Sonnie Dash","email":"sdash1a@ibm.com","gender":"Male","address":"Olopa"},
{"id":48,"first_name":"Olia Vigurs","email":"ovigurs1b@virginia.edu","gender":"Female","address":"Huyuan"},
{"id":49,"first_name":"Sebastien Juden","email":"sjuden1c@google.ca","gender":"Male","address":"Mesyagutovo"},
{"id":50,"first_name":"See Ratazzi","email":"sratazzi1d@flickr.com","gender":"Male","address":"Fundong"},
{"id":51,"first_name":"Wendall Attaway","email":"wattaway1e@ameblo.jp","gender":"Male","address":"Imġarr"},
{"id":52,"first_name":"Mandel Mott","email":"mmott1f@pagesperso-orange.fr","gender":"Male","address":"Smederevo"},
{"id":53,"first_name":"Lucian Halbord","email":"lhalbord1g@psu.edu","gender":"Male","address":"Duboka"},
{"id":54,"first_name":"Aubree Callard","email":"acallard1h@google.it","gender":"Female","address":"Gōdo"},
{"id":55,"first_name":"Karna Aleksandrov","email":"kaleksandrov1i@toplist.cz","gender":"Female","address":"Bergen"},
{"id":56,"first_name":"Cymbre Macieiczyk","email":"cmacieiczyk1j@diigo.com","gender":"Female","address":"Březí"},
{"id":57,"first_name":"Abbott Rangle","email":"arangle1k@indiegogo.com","gender":"Male","address":"Fundación"},
{"id":58,"first_name":"Bevan Claus","email":"bclaus1l@nifty.com","gender":"Male","address":"Li’an"},
{"id":59,"first_name":"Brier Ummfrey","email":"bummfrey1m@youtube.com","gender":"Female","address":"Masohi"},
{"id":60,"first_name":"Mada MacQuarrie","email":"mmacquarrie1n@shop-pro.jp","gender":"Female","address":"Pacaembu"},
{"id":61,"first_name":"Becka Marsham","email":"bmarsham1o@arstechnica.com","gender":"Female","address":"Malabor"},
{"id":62,"first_name":"Erny Hydes","email":"ehydes1p@istockphoto.com","gender":"Male","address":"Ngulahan"},
{"id":63,"first_name":"Kippar Mosedale","email":"kmosedale1q@blogs.com","gender":"Male","address":"Takahama"},
{"id":64,"first_name":"Wren Gives","email":"wgives1r@nymag.com","gender":"Female","address":"Fort Smith"},
{"id":65,"first_name":"Brear Housby","email":"bhousby1s@sakura.ne.jp","gender":"Female","address":"Oehaunu"},
{"id":66,"first_name":"Ami Badger","email":"abadger1t@adobe.com","gender":"Female","address":"Sambir"},
{"id":67,"first_name":"Dana Briereton","email":"dbriereton1u@twitpic.com","gender":"Female","address":"Wan’an"},
{"id":68,"first_name":"Floris Cadwaladr","email":"fcadwaladr1v@bluehost.com","gender":"Agender","address":"Namyang-dong"},
{"id":69,"first_name":"Maire MacGibbon","email":"mmacgibbon1w@marriott.com","gender":"Female","address":"Ronneby"},
{"id":70,"first_name":"Dita Volante","email":"dvolante1x@slideshare.net","gender":"Female","address":"Jalaud"},
{"id":71,"first_name":"Ema Syddie","email":"esyddie1y@fastcompany.com","gender":"Female","address":"La Reforma"},
{"id":72,"first_name":"Osmond Davey","email":"odavey1z@netlog.com","gender":"Male","address":"Fortaleza"},
{"id":73,"first_name":"Bendite Jentges","email":"bjentges20@ask.com","gender":"Female","address":"Caleta Olivia"},
{"id":74,"first_name":"Steffi Bannester","email":"sbannester21@about.com","gender":"Female","address":"Anda"},
{"id":75,"first_name":"Sig Schoolfield","email":"sschoolfield22@gmpg.org","gender":"Male","address":"Chengguan"},
{"id":76,"first_name":"Sapphira Force","email":"sforce23@ucla.edu","gender":"Female","address":"Buenavista"},
{"id":77,"first_name":"Gaultiero Stickler","email":"gstickler24@privacy.gov.au","gender":"Male","address":"Jīma"},
{"id":78,"first_name":"Aurie Mighele","email":"amighele25@woothemes.com","gender":"Female","address":"Ivoti"},
{"id":79,"first_name":"Ree Varty","email":"rvarty26@uol.com.br","gender":"Genderqueer","address":"Lisia Góra"},
{"id":80,"first_name":"Branden Keemer","email":"bkeemer27@reuters.com","gender":"Male","address":"Peukanbada"},
{"id":81,"first_name":"Millisent Allatt","email":"mallatt28@nydailynews.com","gender":"Female","address":"Termas de Río Hondo"},
{"id":82,"first_name":"Tobey Gaythorpe","email":"tgaythorpe29@edublogs.org","gender":"Female","address":"Drásov"},
{"id":83,"first_name":"Marni Labrenz","email":"mlabrenz2a@home.pl","gender":"Female","address":"Hanshou"},
{"id":84,"first_name":"Belinda Goodrum","email":"bgoodrum2b@people.com.cn","gender":"Female","address":"Talnakh"},
{"id":85,"first_name":"Denis Chimienti","email":"dchimienti2c@wikipedia.org","gender":"Male","address":"Arroteia"},
{"id":86,"first_name":"Rafe Bramich","email":"rbramich2d@usda.gov","gender":"Male","address":"Ershilipu"},
{"id":87,"first_name":"Mitzi Tomaskov","email":"mtomaskov2e@purevolume.com","gender":"Female","address":"Lutian"},
{"id":88,"first_name":"Maje Barr","email":"mbarr2f@blinklist.com","gender":"Male","address":"Caibarién"},
{"id":89,"first_name":"Rouvin Patrone","email":"rpatrone2g@hostgator.com","gender":"Male","address":"Dongming Chengguanzhen"},
{"id":90,"first_name":"Lorne Arrigucci","email":"larrigucci2h@moonfruit.com","gender":"Female","address":"Bei"},
{"id":91,"first_name":"Cortney Russe","email":"crusse2i@ucsd.edu","gender":"Female","address":"Yongdong"},
{"id":92,"first_name":"Tilly Farrance","email":"tfarrance2j@yelp.com","gender":"Polygender","address":"Nancy"},
{"id":93,"first_name":"Mariquilla Holston","email":"mholston2k@examiner.com","gender":"Female","address":"Xijiang"},
{"id":94,"first_name":"Gilles Linay","email":"glinay2l@photobucket.com","gender":"Male","address":"Barda"},
{"id":95,"first_name":"Arlie Thebeau","email":"athebeau2m@stumbleupon.com","gender":"Female","address":"Báguanos"},
{"id":96,"first_name":"Sharona Presdie","email":"spresdie2n@macromedia.com","gender":"Female","address":"Lebak"},
{"id":97,"first_name":"Ritchie Tesoe","email":"rtesoe2o@bloomberg.com","gender":"Genderqueer","address":"Yaxi"},
{"id":98,"first_name":"Demetri Lakeman","email":"dlakeman2p@is.gd","gender":"Male","address":"Banyue"},
{"id":99,"first_name":"Hans Menure","email":"hmenure2q@feedburner.com","gender":"Male","address":"Kaoshan"},
{"id":100,"first_name":"Padraig Whaymand","email":"pwhaymand2r@soundcloud.com","gender":"Male","address":"Bordeaux"}]